django_tests-1.8.3.dist-info/WHEEL
django_tests-1.8.3.dist-info/RECORD
django_tests-1.8.3.dist-info/METADATA
django_tests-1.8.3.dist-info/top_level.txt
django_tests-1.8.3.dist-info/DESCRIPTION.rst
django_tests-1.8.3.dist-info/LICENSE.txt
django_tests-1.8.3.dist-info/metadata.json
django_tests-1.8.3.dist-info/pbr.json
django_tests/urls.py
django_tests/runtests.py
django_tests/test_sqlite.py
django_tests/__init__.py
django_tests/sites_tests/tests.py
django_tests/sites_tests/__init__.py
django_tests/user_commands/tests.py
django_tests/user_commands/models.py
django_tests/user_commands/__init__.py
django_tests/user_commands/management/__init__.py
django_tests/user_commands/management/commands/leave_locale_alone_true.py
django_tests/user_commands/management/commands/leave_locale_alone_false.py
django_tests/user_commands/management/commands/dance.py
django_tests/user_commands/management/commands/hal.py
django_tests/user_commands/management/commands/optparse_cmd.py
django_tests/user_commands/management/commands/__init__.py
django_tests/user_commands/management/commands/transaction.py
django_tests/file_uploads/tests.py
django_tests/file_uploads/urls.py
django_tests/file_uploads/uploadhandler.py
django_tests/file_uploads/views.py
django_tests/file_uploads/models.py
django_tests/file_uploads/__init__.py
django_tests/m2m_and_m2o/tests.py
django_tests/m2m_and_m2o/models.py
django_tests/m2m_and_m2o/__init__.py
django_tests/forms_tests/urls.py
django_tests/forms_tests/views.py
django_tests/forms_tests/models.py
django_tests/forms_tests/__init__.py
django_tests/forms_tests/tests/test_validators.py
django_tests/forms_tests/tests/tests.py
django_tests/forms_tests/tests/test_widgets.py
django_tests/forms_tests/tests/test_input_formats.py
django_tests/forms_tests/tests/test_regressions.py
django_tests/forms_tests/tests/test_utils.py
django_tests/forms_tests/tests/test_formsets.py
django_tests/forms_tests/tests/test_media.py
django_tests/forms_tests/tests/test_fields.py
django_tests/forms_tests/tests/test_forms.py
django_tests/forms_tests/tests/test_extra.py
django_tests/forms_tests/tests/test_error_messages.py
django_tests/forms_tests/tests/__init__.py
django_tests/bash_completion/tests.py
django_tests/bash_completion/__init__.py
